<?xml version="1.0" encoding="utf-8"?>
<search>
  
  
  
  <entry>
    <title>与我常在</title>
    <link href="/2025/03/15/%E4%B8%8E%E6%88%91%E5%B8%B8%E5%9C%A8/"/>
    <url>/2025/03/15/%E4%B8%8E%E6%88%91%E5%B8%B8%E5%9C%A8/</url>
    
    <content type="html"><![CDATA[<blockquote><p>在一起看每出戏</p><p>在一起叹每口气</p><p>再细尝 同偕到老的况味</p><p>…</p></blockquote><p>Eason 在采访里说上了年纪才知道《与我常在》是悲词，怪不得是慵懒的唱腔，甚至能听出一点点笑意。直到</p><blockquote><p>除非你是我 才可与我同在</p><p>一个人 从镜内发展恋爱</p></blockquote><p>感觉这两句形容此时此刻我的状态很合适。这算是高级的孤独感吗？</p><p>只怕也不能算，至多可以算是自由又寂寞吧。时间就这么分分秒秒过去，说没有一丝迟疑是假的。可总又不甘心，还是妄想着能遇到一个绝对合拍的灵魂。可茫茫人海，又往何处去寻。</p><p>就像拿着词去谱曲一样，既然要匹配，起码得拿出一半的信息。思来想去，还是要先把我这首不知好坏的词写出来，祈望着某天得某人谱完这整首歌。</p><p>这篇算是博客的开头吧，希望读到我的文字的诸位，健康顺遂，与我常在。</p><blockquote><p>一个人 同偕到老不算运气</p></blockquote><p>这末尾一句，也太悲伤了一点。</p>]]></content>
    
    
    <categories>
      
      <category>杂谈</category>
      
    </categories>
    
    
    <tags>
      
      <tag>杂谈</tag>
      
      <tag>音乐</tag>
      
    </tags>
    
  </entry>
  
  
  
  
</search>
